{
    "2024": [
        375776,
        3,
        382502,
        366727,
        356137,
        366315,
        367572,
        99798,
        371671,
        343094
    ],
    "2610": [
        3,
        516,
        63116,
        94671,
        312753,
        382067,
        373368,
        363898,
        308797
    ],
    "2185": [
        101892,
        98821,
        52235,
        349709,
        355349,
        353302,
        345624,
        56353,
        2042,
        355363,
        356910,
        355375,
        1077,
        6711,
        115255,
        57,
        309310,
        356414,
        321602,
        588,
        100429,
        2638,
        117839,
        2655,
        353377,
        352355,
        357994,
        358509,
        332406,
        345720,
        1149,
        3715,
        115848,
        9866,
        9356,
        91789,
        65678,
        89744,
        71319,
        384156,
        354984,
        356010,
        98475,
        71852,
        98477,
        368838,
        331975,
        58578,
        355027,
        359635,
        58580,
        100562,
        56024,
        352477,
        86751,
        355557,
        383211,
        70381,
        69358,
        99581,
        123646,
        98566,
        64262,
        362775,
        123679,
        351521,
        376612,
        354597,
        123688,
        355114,
        6972,
        115017,
        360779,
        342351,
        123728,
        54616,
        352600,
        70491,
        3935,
        95073,
        355170,
        357220,
        58727,
        362357,
        357238,
        354692,
        57225,
        337804,
        354701,
        354702,
        8590,
        357882,
        73115,
        353190,
        347049,
        349101,
        335790,
        77744,
        349106,
        355766,
        348094,
        346571,
        355277,
        78286,
        342998,
        98776,
        76762,
        85981,
        123364,
        54246,
        62440,
        123370,
        100334,
        354803,
        342004,
        344565,
        71162,
        136703
    ],
    "3": [
        61440,
        3,
        8,
        141,
        374673,
        119833,
        2074,
        28,
        354976,
        382497,
        297249,
        83750,
        140586,
        2477,
        138926,
        140077,
        120121,
        441,
        371900,
        113990,
        841,
        134606,
        381903,
        2257,
        137810,
        850,
        213,
        374875,
        374492,
        383475,
        362355,
        114171,
        121342
    ],
    "506": [
        92513,
        78131,
        92510
    ],
    "17": [
        3,
        302052,
        370409,
        362351,
        384145,
        384146,
        383219,
        384151,
        384154
    ],
    "600": [
        6392,
        89187,
        3,
        381897,
        122281,
        88589,
        311022,
        337265,
        332406,
        66870,
        382264,
        299036,
        384157,
        3806
    ],
    "774": [
        384159,
        3,
        50921,
        384139,
        313817,
        384144,
        308528,
        320180,
        352436,
        384150,
        113782,
        315929,
        116539,
        382719
    ],
    "2383": [
        3,
        369961,
        370250,
        370955,
        381007,
        372984,
        370265
    ],
    "458": [
        117889,
        363122,
        383475,
        134606
    ],
    "6": [
        99360,
        111619,
        96196,
        97215
    ],
    "2374": [
        3,
        346676
    ],
    "2514": [
        377809,
        56402,
        3,
        384149
    ],
    "180": [
        89410,
        3,
        96456,
        134606,
        384147,
        94004,
        383475,
        80599,
        89658
    ],
    "952": [
        3,
        56868,
        303975,
        308887,
        296788,
        81973,
        65431
    ],
    "109": [
        3,
        302052,
        370409,
        345002,
        335569,
        346676
    ],
    "2799": [
        3,
        310699,
        382128,
        204793,
        61946
    ],
    "2325": [
        329505,
        86602,
        3,
        81973
    ],
    "2834": [
        3,
        346676
    ],
    "2637": [
        352618,
        3
    ],
    "2321": [
        384160,
        3,
        384148
    ],
    "300": [
        90369,
        3,
        95268,
        77445,
        81974,
        85335,
        142491
    ],
    "2387": [
        367224,
        331759
    ],
    "1728": [
        373641,
        371097,
        3
    ],
    "286": [
        3,
        383164,
        356693
    ],
    "87": [
        61136,
        5076,
        384152,
        106200
    ],
    "1885": [
        342338,
        3
    ],
    "1429": [
        3,
        85556,
        328395
    ],
    "9": [
        85,
        69654
    ],
    "1935": [
        349337,
        366779
    ],
    "426": [
        379824,
        3
    ],
    "2713": [
        819,
        377715,
        382620
    ],
    "499": [
        76651,
        383211,
        2590
    ],
    "2788": [
        135337,
        135324
    ],
    "2728": [
        3,
        384153,
        382339
    ],
    "948": [
        58137,
        60794,
        3,
        83165
    ],
    "1039": [
        3,
        97822,
        116404,
        373434,
        89629,
        384158,
        89631
    ],
    "2792": [
        9019,
        3
    ],
    "518": [
        93488,
        3
    ],
    "1332": [
        3,
        384155
    ],
    "950": [
        3,
        2557
    ],
    "86": [
        384152,
        376174
    ],
    "2190": [
        359346,
        137891
    ],
    "2833": [
        180825,
        3
    ]
}